frigg/common_crawl/extractors/audio.py
frigg/common_crawl/extractors/base.py
frigg/common_crawl/extractors/image.py
frigg/common_crawl/extractors/text.py
frigg/common_crawl/extractors/video.py
frigg-0.1.2.dist-info/METADATA
frigg-0.1.2.dist-info/WHEEL
frigg-0.1.2.dist-info/top_level.txt
frigg-0.1.2.dist-info/RECORD
